[
  {
    "id": 1,
    "name": "محل",
    "locations": [
      {
        "id": 1,
        "name": "واجهة محل شرقي",
        "epcs": [
          {
            "epc": "0005",
            "pn": "حلق ألماس"
          },
          {
            "epc": "0006",
            "pn": "سنسال ذهب فخم"
          },
          {
            "epc": "0007",
            "pn": "منتج 009"
          },
          {
            "epc": "0008",
            "pn": "منتج 010"
          },
          {
            "epc": "0009",
            "pn": "منتج 011"
          },
          {
            "epc": "0010",
            "pn": "منتج 012"
          },
          {
            "epc": "0011",
            "pn": "منتج 013"
          },
          {
            "epc": "0012",
            "pn": "منتج 014"
          },
          {
            "epc": "0013",
            "pn": "منتج 015"
          },
          {
            "epc": "0014",
            "pn": "منتج 016"
          },
          {
            "epc": "0015",
            "pn": "منتج 017"
          },
          {
            "epc": "0016",
            "pn": "منتج 018"
          },
          {
            "epc": "0017",
            "pn": "منتج 019"
          },
          {
            "epc": "0018",
            "pn": "منتج 020"
          },
          {
            "epc": "0019",
            "pn": "منتج 021"
          },
          {
            "epc": "0020",
            "pn": "منتج 022"
          },
          {
            "epc": "0021",
            "pn": "منتج 023"
          },
          {
            "epc": "0022",
            "pn": "منتج 024"
          },
          {
            "epc": "0023",
            "pn": "منتج 025"
          },
          {
            "epc": "0024",
            "pn": "منتج 026"
          },
          {
            "epc": "0025",
            "pn": "منتج 027"
          },
          {
            "epc": "0026",
            "pn": "منتج 028"
          },
          {
            "epc": "0027",
            "pn": "منتج 029"
          },
          {
            "epc": "0028",
            "pn": "منتج 030"
          },
          {
            "epc": "0029",
            "pn": "منتج 031"
          },
          {
            "epc": "0030",
            "pn": "منتج 032"
          },
          {
            "epc": "0031",
            "pn": "منتج 033"
          },
          {
            "epc": "0032",
            "pn": "منتج 034"
          },
          {
            "epc": "0033",
            "pn": "منتج 035"
          },
          {
            "epc": "0034",
            "pn": "منتج 036"
          },
          {
            "epc": "0035",
            "pn": "منتج 037"
          },
          {
            "epc": "0036",
            "pn": "منتج 038"
          },
          {
            "epc": "0037",
            "pn": "منتج 039"
          },
          {
            "epc": "0038",
            "pn": "منتج 040"
          },
          {
            "epc": "0039",
            "pn": "منتج 041"
          },
          {
            "epc": "0040",
            "pn": "منتج 042"
          },
          {
            "epc": "0041",
            "pn": "منتج 043"
          },
          {
            "epc": "0042",
            "pn": "منتج 044"
          },
          {
            "epc": "0043",
            "pn": "منتج 045"
          },
          {
            "epc": "0044",
            "pn": "منتج 046"
          },
          {
            "epc": "0045",
            "pn": "منتج 047"
          },
          {
            "epc": "0046",
            "pn": "منتج 048"
          },
          {
            "epc": "0047",
            "pn": "منتج 049"
          },
          {
            "epc": "0048",
            "pn": "منتج 050"
          },
          {
            "epc": "0049",
            "pn": "منتج 051"
          },
          {
            "epc": "0050",
            "pn": "منتج 052"
          },
          {
            "epc": "0051",
            "pn": "منتج 053"
          },
          {
            "epc": "0052",
            "pn": "منتج 054"
          },
          {
            "epc": "0053",
            "pn": "منتج 055"
          },
          {
            "epc": "0054",
            "pn": "منتج 056"
          },
          {
            "epc": "0055",
            "pn": "منتج 057"
          },
          {
            "epc": "0056",
            "pn": "منتج 058"
          },
          {
            "epc": "0057",
            "pn": "منتج 059"
          },
          {
            "epc": "0058",
            "pn": "منتج 060"
          },
          {
            "epc": "0059",
            "pn": "منتج 061"
          },
          {
            "epc": "0060",
            "pn": "منتج 062"
          },
          {
            "epc": "0061",
            "pn": "منتج 063"
          },
          {
            "epc": "0062",
            "pn": "منتج 064"
          },
          {
            "epc": "0063",
            "pn": "منتج 065"
          },
          {
            "epc": "0064",
            "pn": "منتج 066"
          },
          {
            "epc": "0065",
            "pn": "منتج 067"
          },
          {
            "epc": "0066",
            "pn": "منتج 068"
          },
          {
            "epc": "0067",
            "pn": "منتج 069"
          },
          {
            "epc": "0068",
            "pn": "منتج 070"
          },
          {
            "epc": "0069",
            "pn": "منتج 071"
          },
          {
            "epc": "0070",
            "pn": "منتج 072"
          },
          {
            "epc": "0071",
            "pn": "منتج 073"
          },
          {
            "epc": "0072",
            "pn": "منتج 074"
          },
          {
            "epc": "0073",
            "pn": "منتج 075"
          },
          {
            "epc": "0074",
            "pn": "منتج 076"
          },
          {
            "epc": "0075",
            "pn": "منتج 077"
          },
          {
            "epc": "0076",
            "pn": "منتج 078"
          },
          {
            "epc": "0077",
            "pn": "منتج 079"
          },
          {
            "epc": "0078",
            "pn": "منتج 080"
          },
          {
            "epc": "0079",
            "pn": "منتج 081"
          },
          {
            "epc": "0080",
            "pn": "منتج 082"
          },
          {
            "epc": "0081",
            "pn": "منتج 083"
          },
          {
            "epc": "0082",
            "pn": "منتج 084"
          },
          {
            "epc": "0083",
            "pn": "منتج 085"
          },
          {
            "epc": "0084",
            "pn": "منتج 086"
          },
          {
            "epc": "0085",
            "pn": "منتج 087"
          },
          {
            "epc": "0086",
            "pn": "منتج 088"
          },
          {
            "epc": "0087",
            "pn": "منتج 089"
          },
          {
            "epc": "0088",
            "pn": "منتج 090"
          },
          {
            "epc": "0089",
            "pn": "منتج 091"
          },
          {
            "epc": "0090",
            "pn": "منتج 092"
          },
          {
            "epc": "0091",
            "pn": "منتج 093"
          },
          {
            "epc": "0092",
            "pn": "منتج 094"
          },
          {
            "epc": "0093",
            "pn": "منتج 095"
          },
          {
            "epc": "0094",
            "pn": "منتج 096"
          },
          {
            "epc": "0095",
            "pn": "منتج 097"
          },
          {
            "epc": "0096",
            "pn": "منتج 098"
          },
          {
            "epc": "0097",
            "pn": "منتج 099"
          },
          {
            "epc": "0098",
            "pn": "جديد"
          },
          {
            "epc": "0099",
            "pn": "جديد"
          },
          {
            "epc": "0100",
            "pn": "تست 2"
          },
          {
            "epc": "0101",
            "pn": "LLLLL"
          },
          {
            "epc": "0102",
            "pn": "vbgbbb"
          },
          {
            "epc": "0103",
            "pn": "vbgbbb"
          },
          {
            "epc": "0104",
            "pn": "qwqwqw"
          },
          {
            "epc": "000000000000000000000107",
            "pn": " سنسال ذهب سنسال ذهب سنسال ذهب سنسال ذهب"
          },
          {
            "epc": "000000000000000000000108",
            "pn": "خاتم ذهب مثني"
          },
          {
            "epc": "000000000000000000000109",
            "pn": "خاتم ذهب مثني"
          },
          {
            "epc": "000000000000000000000110",
            "pn": "خاتم ذهب مثني"
          },
          {
            "epc": "000000000000000000000111",
            "pn": "محبس سادة f"
          },
          {
            "epc": "000000000000000000000112",
            "pn": "محبس سادة f"
          },
          {
            "epc": "000000000000000000000113",
            "pn": "محبس سادة f"
          },
          {
            "epc": "000000000000000000000114",
            "pn": "محبس سادة f"
          },
          {
            "epc": "000000000000000000000115",
            "pn": "محبس سادة f"
          },
          {
            "epc": "000000000000000000000116",
            "pn": "محبس سادة f"
          },
          {
            "epc": "000000000000000000000117",
            "pn": "محبس سادة f"
          },
          {
            "epc": "000000000000000000000118",
            "pn": "محبس سادة f"
          },
          {
            "epc": "000000000000000000000119",
            "pn": "محبس سادة f"
          },
          {
            "epc": "000000000000000000000120",
            "pn": "منتج 009"
          },
          {
            "epc": "000000000000000000000121",
            "pn": "منتج 009"
          },
          {
            "epc": "000000000000000000000122",
            "pn": "منتج 009"
          },
          {
            "epc": "000000000000000000000123",
            "pn": "منتج 009"
          },
          {
            "epc": "000000000000000000000124",
            "pn": "منتج 009"
          },
          {
            "epc": "000000000000000000000125",
            "pn": "منتج 012"
          },
          {
            "epc": "000000000000000000000126",
            "pn": "منتج 012"
          },
          {
            "epc": "000000000000000000000127",
            "pn": "منتج 012"
          },
          {
            "epc": "000000000000000000000128",
            "pn": "خاتم ذهب مثني"
          },
          {
            "epc": "000000000000000000000129",
            "pn": "خاتم ذهب مثني"
          },
          {
            "epc": "000000000000000000000130",
            "pn": "سنسال ذهب فخم"
          },
          {
            "epc": "000000000000000000000131",
            "pn": "سنسال ذهب فخم"
          },
          {
            "epc": "000000000000000000000132",
            "pn": "سنسال ذهب فخم"
          },
          {
            "epc": "EEE000000000000000000133",
            "pn": "سنسال ذهب فخم"
          },
          {
            "epc": "000000000000000000000134",
            "pn": "سنسال ذهب فخم"
          },
          {
            "epc": "000000000000000000000135",
            "pn": "سنسال ذهب فخم"
          },
          {
            "epc": "000000000000000000000136",
            "pn": "سنسال ذهب فخم"
          }
        ]
      },
      {
        "id": 2,
        "name": "واجهة محل غربي",
        "epcs": [
          {
            "epc": "0002",
            "pn": " سنسال ذهب سنسال ذهب سنسال ذهب سنسال ذهب"
          }
        ]
      },
      {
        "id": 3,
        "name": "فيترين",
        "epcs": []
      },
      {
        "id": 6,
        "name": "dfsdf",
        "epcs": []
      }
    ]
  },
  {
    "id": 2,
    "name": "مستودع",
    "locations": [
      {
        "id": 4,
        "name": "طابق سفلي",
        "epcs": [
          {
            "epc": "0004",
            "pn": "خاتم ذهب مثني"
          }
        ]
      },
      {
        "id": 5,
        "name": "طابق أول",
        "epcs": [
          {
            "epc": "0003",
            "pn": "خاتم ذهب مثني"
          }
        ]
      }
    ]
  },
  {
    "id": 3,
    "name": "محلس",
    "locations": [
      {
        "id": 1,
        "name": "aTest2",
        "epcs": []
      },
      {
        "id": 2,
        "name": "Test2",
        "epcs": []
      }
    ]
  },
  {
    "id": 4,
    "name": "تست",
    "locations": [
      {
        "id": 1,
        "name": "Test1",
        "epcs": []
      },
      {
        "id": 2,
        "name": "Test2",
        "epcs": []
      }
    ]
  }
]